me3cs/__init__.py
me3cs/cross_validation/__init__.py
me3cs/cross_validation/cross_validation.py
me3cs/cross_validation/cross_validation_model.py
me3cs/cross_validation/cross_validation_predictor.py
me3cs/cross_validation/cross_validation_preprocessing.py
me3cs/cross_validation/cross_validation_split.py
me3cs/cross_validation/cross_validation_types.py
me3cs/framework/__init__.py
me3cs/framework/base_model.py
me3cs/framework/branch.py
me3cs/framework/data.py
me3cs/framework/decomposition_model.py
me3cs/framework/log.py
me3cs/framework/model.py
me3cs/framework/outlier_detection.py
me3cs/framework/regression_model.py
me3cs/framework/results.py
me3cs/framework/helper_classes/__init__.py
me3cs/framework/helper_classes/handle_input.py
me3cs/framework/helper_classes/link.py
me3cs/framework/helper_classes/options.py
me3cs/metrics/__init__.py
me3cs/metrics/regression/__init__.py
me3cs/metrics/regression/diagnostics.py
me3cs/metrics/regression/metrics.py
me3cs/metrics/regression/results.py
me3cs/misc/__init__.py
me3cs/misc/handle_data.py
me3cs/misc/metrics.py
me3cs/misc/preprocessing.py
me3cs/missing_data/__init__.py
me3cs/missing_data/bootstrapping.py
me3cs/missing_data/imputation.py
me3cs/missing_data/interpolation.py
me3cs/missing_data/missing_data.py
me3cs/models/__init__.py
me3cs/models/decomposition/__init__.py
me3cs/models/decomposition/decomposition_diagnostics.py
me3cs/models/decomposition/decomposition_results.py
me3cs/models/decomposition/pca.py
me3cs/models/regression/__init__.py
me3cs/models/regression/cls.py
me3cs/models/regression/mlr.py
me3cs/models/regression/pcr.py
me3cs/models/regression/pls.py
me3cs/models/regression/svm.py
me3cs/preprocessing/__init__.py
me3cs/preprocessing/base.py
me3cs/preprocessing/called.py
me3cs/preprocessing/filtering.py
me3cs/preprocessing/normalisation.py
me3cs/preprocessing/preprocessing.py
me3cs/preprocessing/scaling.py
me3cs/preprocessing/standardisation.py
me3cs-0.1.6.dist-info/LICENSE.txt
me3cs-0.1.6.dist-info/METADATA
me3cs-0.1.6.dist-info/WHEEL
me3cs-0.1.6.dist-info/top_level.txt
me3cs-0.1.6.dist-info/RECORD
