Metadata-Version: 2.1
Name: me3cs
Version: 0.1.6
Home-page: https://github.com/DanielHoj/me3cs
Author: Daniel Andreas Njust Høj
Author-email: d.njust.hoej@gmail.com
License: BSD 3-clause
Keywords: chemometrics
License-File: LICENSE.txt
Requires-Dist: pandas
Requires-Dist: numpy
Requires-Dist: scipy
